MANIFEST.in
RELEASE-VERSION
setup.cfg
setup.py
version.py
throw/__init__.py
throw/commandline.py
throw/config.py
throw/identity.py
throw/terminalinterface.py
throw/throw.py
throw/thrower.py
throw.egg-info/PKG-INFO
throw.egg-info/SOURCES.txt
throw.egg-info/dependency_links.txt
throw.egg-info/entry_points.txt
throw.egg-info/requires.txt
throw.egg-info/top_level.txt
throw/minus/__init__.py
throw/minus/minus.py
throw/tests/__init__.py
throw/tests/test_all.py