Metadata-Version: 1.0
Name: throw
Version: 0.1-15-gb88c
Summary: Simply share files from the command line
Home-page: http://github.com/rjw57/throw
Author: Rich Wareham
Author-email: rjw57@cam.ac.uk
License: Apache 2.0
Keywords: file sharing throw email
Platform: UNKNOWN
Classifier: Development Status :: 2 - Pre-Alpha
Classifier: Environment :: Console
Classifier: Intended Audience :: End Users/Desktop
Classifier: License :: OSI Approved :: Apache Software License
Classifier: Natural Language :: English
Classifier: Operating System :: OS Independent
Classifier: Topic :: Communications
Classifier: Topic :: Communications :: Email
Classifier: Topic :: Communications :: File Sharing
Classifier: Topic :: Utilities
Classifier: Programming Language :: Python
Classifier: Programming Language :: Python :: 3
